README.txt
setup.py
milieu/__init__.py
milieu/__init__.pyc
test/__init__.py
test/test_main.py
unholster.milieu.egg-info/PKG-INFO
unholster.milieu.egg-info/SOURCES.txt
unholster.milieu.egg-info/dependency_links.txt
unholster.milieu.egg-info/top_level.txt