Metadata-Version: 1.1
Name: unholster.milieu
Version: 1.0.0
Summary: Flexible parameter management
Home-page: https://github.com/Unholster/milieu
Author: Andrés Villavicencio
Author-email: andres@unholster.com
License: BSD
Platform: UNKNOWN
Classifier: Development Status :: 5 - Production/Stable
Classifier: Topic :: Utilities
